[
  {
    "course_code": "161003",
    "section": "01",
    "course_name": "헌법I",
    "professor": "김도협",
    "credits": 3,
    "hours": 6,
    "category": "major",
    "classification": "전필",
    "college": "공공인재대학",
    "department": "공공인재법학과",
    "schedule_raw": "월09:30-12:30",
    "times": [{"day": "월", "start": "09:30", "end": "12:30"}],
    "room": "e-강의실",
    "target_year": 1,
    "capacity": 0,
    "notes": "플립러닝(비대면수업 10시간 진행)",
    "is_micro": true
  },
  {
    "course_code": "161003",
    "section": "02",
    "course_name": "헌법I",
    "professor": "김도협",
    "credits": 3,
    "hours": 6,
    "category": "major",
    "classification": "전필",
    "college": "공공인재대학",
    "department": "공공인재법학과",
    "schedule_raw": "목21:20-22:10",
    "times": [{"day": "목", "start": "21:20", "end": "22:10"}],
    "room": "e-learning(온라인2",
    "target_year": 1,
    "capacity": 0,
    "notes": "공공인재법학과 학생전용(재수강불가, 마이크로전공)",
    "is_micro": true
  },
  {
    "course_code": "162500",
    "section": "01",
    "course_name": "***법학입문",
    "professor": "최용준",
    "credits": 3,
    "hours": 6,
    "category": "major",
    "classification": "전선",
    "college": "공공인재대학",
    "department": "공공인재법학과",
    "schedule_raw": "월13:30-15:00, 목15:00-17:00",
    "times": [{"day": "월", "start": "13:30", "end": "15:00"}, {"day": "목", "start": "15:00", "end": "17:00"}],
    "room": "e-강의실",
    "target_year": 1,
    "capacity": 0,
    "notes": "전공입문 교과목임, 융합대아이티학과 온라인10시간 추가진행",
    "is_micro": false
  },
  {
    "course_code": "161049",
    "section": "01",
    "course_name": "형법총론",
    "professor": "최대호",
    "credits": 3,
    "hours": 6,
    "category": "major",
    "classification": "전선",
    "college": "공공인재대학",
    "department": "공공인재법학과",
    "schedule_raw": "수11:30-13:00, 수13:00-13:00",
    "times": [{"day": "수", "start": "11:30", "end": "13:00"}],
    "room": "강의실",
    "target_year": 2,
    "capacity": 0,
    "notes": "융합,인이티(플립러닝비대면수업10시간4시간진행)",
    "is_micro": false
  },
  {
    "course_code": "162097",
    "section": "01",
    "course_name": "물권법",
    "professor": "김도협",
    "credits": 3,
    "hours": 6,
    "category": "major",
    "classification": "전선",
    "college": "공공인재대학",
    "department": "공공인재법학과",
    "schedule_raw": "수15:30-18:25",
    "times": [{"day": "수", "start": "15:30", "end": "18:25"}],
    "room": "A302 - 강의실",
    "target_year": 2,
    "capacity": 0,
    "notes": "융합,인이티(플립러닝비대면수업10시간진행)",
    "is_micro": false
  },
  {
    "course_code": "165001",
    "section": "01",
    "course_name": "행정법총론",
    "professor": "최용준",
    "credits": 3,
    "hours": 6,
    "category": "major",
    "classification": "전선",
    "college": "공공인재대학",
    "department": "공공인재법학과",
    "schedule_raw": "월00:00-11:30, 목00:00-11:30",
    "times": [{"day": "월", "start": "10:00", "end": "11:30"}, {"day": "목", "start": "10:00", "end": "11:30"}],
    "room": "고양A/V강의실",
    "target_year": 2,
    "capacity": 0,
    "notes": "",
    "is_micro": false
  },
  {
    "course_code": "165001",
    "section": "02",
    "course_name": "행정법총론",
    "professor": "최용준",
    "credits": 3,
    "hours": 6,
    "category": "major",
    "classification": "전선",
    "college": "공공인재대학",
    "department": "공공인재법학과",
    "schedule_raw": "수19:15-20:05",
    "times": [{"day": "수", "start": "19:15", "end": "20:05"}],
    "room": "e-learning(온라인2",
    "target_year": 2,
    "capacity": 0,
    "notes": "원격수업(법학과 학생전용재수강학생불가)",
    "is_micro": false
  },
  {
    "course_code": "165011",
    "section": "01",
    "course_name": "헌법재판과판례",
    "professor": "김도협",
    "credits": 3,
    "hours": 6,
    "category": "major",
    "classification": "전선",
    "college": "공공인재대학",
    "department": "공공인재법학과",
    "schedule_raw": "금10:00-13:00",
    "times": [{"day": "금", "start": "10:00", "end": "13:00"}],
    "room": "사302 - 강의실",
    "target_year": 2,
    "capacity": 0,
    "notes": "",
    "is_micro": false
  },
  {
    "course_code": "165015",
    "section": "01",
    "course_name": "LEET연습",
    "professor": "최대호",
    "credits": 3,
    "hours": 6,
    "category": "major",
    "classification": "전선",
    "college": "공공인재대학",
    "department": "공공인재법학과",
    "schedule_raw": "수15:30-17:00",
    "times": [{"day": "수", "start": "15:30", "end": "17:00"}],
    "room": "",
    "target_year": 2,
    "capacity": 0,
    "notes": "",
    "is_micro": false
  },
  {
    "course_code": "165016",
    "section": "01",
    "course_name": "상법I",
    "professor": "이종",
    "credits": 3,
    "hours": 6,
    "category": "major",
    "classification": "전선",
    "college": "공공인재대학",
    "department": "공공인재법학과",
    "schedule_raw": "목16:30-19:15",
    "times": [{"day": "목", "start": "16:30", "end": "19:15"}],
    "room": "사302 - 강의실",
    "target_year": 2,
    "capacity": 0,
    "notes": "융합인자전형창의도전전공",
    "is_micro": false
  },
  {
    "course_code": "165019",
    "section": "01",
    "course_name": "공직선거법",
    "professor": "김도협",
    "credits": 3,
    "hours": 6,
    "category": "major",
    "classification": "전선",
    "college": "공공인재대학",
    "department": "공공인재법학과",
    "schedule_raw": "월13:30-16:30",
    "times": [{"day": "월", "start": "13:30", "end": "16:30"}],
    "room": "",
    "target_year": 3,
    "capacity": 0,
    "notes": "융합인이티(플립러닝비대면수업10시간진행)",
    "is_micro": false
  },
  {
    "course_code": "165020",
    "section": "01",
    "course_name": "가족정책법",
    "professor": "천영성",
    "credits": 3,
    "hours": 6,
    "category": "major",
    "classification": "전선",
    "college": "공공인재대학",
    "department": "공공인재법학과",
    "schedule_raw": "화11:30-13:00",
    "times": [{"day": "화", "start": "11:30", "end": "13:00"}],
    "room": "사101 - e-강의실A/V실",
    "target_year": 3,
    "capacity": 0,
    "notes": "",
    "is_micro": true
  },
  {
    "course_code": "165026",
    "section": "01",
    "course_name": "민사소송법실무I",
    "professor": "김영덕",
    "credits": 3,
    "hours": 4,
    "category": "major",
    "classification": "전선",
    "college": "공공인재대학",
    "department": "공공인재법학과",
    "schedule_raw": "수13:30-17:30",
    "times": [{"day": "수", "start": "13:30", "end": "17:30"}],
    "room": "사101 - 고양A/V강의실",
    "target_year": 3,
    "capacity": 0,
    "notes": "",
    "is_micro": false
  },
  {
    "course_code": "165031",
    "section": "01",
    "course_name": "형사소송법I",
    "professor": "최대호",
    "credits": 3,
    "hours": 4,
    "category": "major",
    "classification": "전선",
    "college": "공공인재대학",
    "department": "공공인재법학과",
    "schedule_raw": "목13:30-16:30",
    "times": [{"day": "목", "start": "13:30", "end": "16:30"}],
    "room": "사203 - 고양병동취석실",
    "target_year": 3,
    "capacity": 0,
    "notes": "",
    "is_micro": false
  },
  {
    "course_code": "162601",
    "section": "01",
    "course_name": "AI시대의노동법",
    "professor": "이주형",
    "credits": 3,
    "hours": 4,
    "category": "major",
    "classification": "전선",
    "college": "공공인재대학",
    "department": "공공인재법학과",
    "schedule_raw": "",
    "times": [],
    "room": "",
    "target_year": 4,
    "capacity": 0,
    "notes": "",
    "is_micro": false
  },
  {
    "course_code": "165022",
    "section": "01",
    "course_name": "부동산법II",
    "professor": "장욱",
    "credits": 3,
    "hours": 6,
    "category": "major",
    "classification": "전선",
    "college": "공공인재대학",
    "department": "공공인재법학과",
    "schedule_raw": "목09:30-12:30",
    "times": [{"day": "목", "start": "09:30", "end": "12:30"}],
    "room": "",
    "target_year": 4,
    "capacity": 0,
    "notes": "",
    "is_micro": false
  },
  {
    "course_code": "165028",
    "section": "01",
    "course_name": "실용형정법",
    "professor": "",
    "credits": 3,
    "hours": 6,
    "category": "major",
    "classification": "전선",
    "college": "공공인재대학",
    "department": "공공인재법학과",
    "schedule_raw": "",
    "times": [],
    "room": "사101",
    "target_year": 4,
    "capacity": 0,
    "notes": "",
    "is_micro": true
  },
  {
    "course_code": "165029",
    "section": "01",
    "course_name": "실용형정법",
    "professor": "최대호",
    "credits": 3,
    "hours": 6,
    "category": "major",
    "classification": "전선",
    "college": "공공인재대학",
    "department": "공공인재법학과",
    "schedule_raw": "화11:30-13:00, 수13:30-15:00",
    "times": [{"day": "화", "start": "11:30", "end": "13:00"}, {"day": "수", "start": "13:30", "end": "15:00"}],
    "room": "대106 - 컴퓨터A/V실",
    "target_year": 4,
    "capacity": 0,
    "notes": "",
    "is_micro": false
  },
  {
    "course_code": "172001",
    "section": "01",
    "course_name": "행정학원론",
    "professor": "홍성우",
    "credits": 3,
    "hours": 6,
    "category": "major",
    "classification": "전필",
    "college": "공공인재대학",
    "department": "행정정보학과",
    "schedule_raw": "화11:30-13:00, 목11:30-13:00",
    "times": [{"day": "화", "start": "11:30", "end": "13:00"}, {"day": "목", "start": "11:30", "end": "13:00"}],
    "room": "사102 - 강의실",
    "target_year": 1,
    "capacity": 0,
    "notes": "",
    "is_micro": true
  },
  {
    "course_code": "172501",
    "section": "01",
    "course_name": "***기초행정학",
    "professor": "고대유",
    "credits": 3,
    "hours": 6,
    "category": "major",
    "classification": "전선",
    "college": "공공인재대학",
    "department": "행정정보학과",
    "schedule_raw": "화15:30-17:00, 목15:30-17:00",
    "times": [{"day": "화", "start": "15:30", "end": "17:00"}, {"day": "목", "start": "15:30", "end": "17:00"}],
    "room": "",
    "target_year": 1,
    "capacity": 0,
    "notes": "전공입문 교과목임",
    "is_micro": false
  },
  {
    "course_code": "175029",
    "section": "01",
    "course_name": "행정과컴퓨터프로그래밍",
    "professor": "윤나나",
    "credits": 3,
    "hours": 6,
    "category": "major",
    "classification": "전선",
    "college": "공공인재대학",
    "department": "행정정보학과",
    "schedule_raw": "월13:30-15:00, 수13:30-15:00",
    "times": [{"day": "월", "start": "13:30", "end": "15:00"}, {"day": "수", "start": "13:30", "end": "15:00"}],
    "room": "사 310 스마트강의실",
    "target_year": 1,
    "capacity": 0,
    "notes": "2018학번 이상은 타 학과의 입문 교과목 이수 시, 최대 6학점까지 일선이 아닌 전선으로 인정",
    "is_micro": false
  },
  {
    "course_code": "172006",
    "section": "01",
    "course_name": "행정조사방법론",
    "professor": "고대유",
    "credits": 3,
    "hours": 6,
    "category": "major",
    "classification": "전선",
    "college": "공공인재대학",
    "department": "행정정보학과",
    "schedule_raw": "화11:30-13:00, 목11:30-13:00",
    "times": [{"day": "화", "start": "11:30", "end": "13:00"}, {"day": "목", "start": "11:30", "end": "13:00"}],
    "room": "",
    "target_year": 2,
    "capacity": 0,
    "notes": "",
    "is_micro": true
  },
  {
    "course_code": "174009",
    "section": "01",
    "course_name": "정책학",
    "professor": "김종관",
    "credits": 3,
    "hours": 6,
    "category": "major",
    "classification": "전선",
    "college": "공공인재대학",
    "department": "행정정보학과",
    "schedule_raw": "월09:30-12:30",
    "times": [{"day": "월", "start": "09:30", "end": "12:30"}],
    "room": "사209 - 강의실",
    "target_year": 2,
    "capacity": 0,
    "notes": "",
    "is_micro": true
  },
  {
    "course_code": "175005",
    "section": "01",
    "course_name": "행정조직관리론",
    "professor": "홍성우",
    "credits": 3,
    "hours": 6,
    "category": "major",
    "classification": "전선",
    "college": "공공인재대학",
    "department": "행정정보학과",
    "schedule_raw": "월10:00-11:30, 수10:00-11:30",
    "times": [{"day": "월", "start": "10:00", "end": "11:30"}, {"day": "수", "start": "10:00", "end": "11:30"}],
    "room": "융합A/V실/대102...",
    "target_year": 2,
    "capacity": 0,
    "notes": "행정정보학과, 부전공공학전공불가",
    "is_micro": true
  },
  {
    "course_code": "175031",
    "section": "01",
    "course_name": "공공데이터베이스관리론",
    "professor": "윤나나",
    "credits": 3,
    "hours": 6,
    "category": "major",
    "classification": "전선",
    "college": "공공인재대학",
    "department": "행정정보학과",
    "schedule_raw": "월13:30-15:00, 수13:30-15:00",
    "times": [{"day": "월", "start": "13:30", "end": "15:00"}, {"day": "수", "start": "13:30", "end": "15:00"}],
    "room": "사 310 스마트강의실",
    "target_year": 2,
    "capacity": 0,
    "notes": "",
    "is_micro": false
  },
  {
    "course_code": "175043",
    "section": "01",
    "course_name": "NCS기반취업설계",
    "professor": "정성우",
    "credits": 3,
    "hours": 6,
    "category": "major",
    "classification": "전선",
    "college": "공공인재대학",
    "department": "행정정보학과",
    "schedule_raw": "월13:30-15:00, 수13:30-15:00",
    "times": [{"day": "월", "start": "13:30", "end": "15:00"}, {"day": "수", "start": "13:30", "end": "15:00"}],
    "room": "",
    "target_year": 2,
    "capacity": 0,
    "notes": "",
    "is_micro": false
  },
  {
    "course_code": "172010",
    "section": "01",
    "course_name": "지방재정론",
    "professor": "고대유",
    "credits": 3,
    "hours": 6,
    "category": "major",
    "classification": "전선",
    "college": "공공인재대학",
    "department": "행정정보학과",
    "schedule_raw": "월10:00-11:30, 수10:00-11:30",
    "times": [{"day": "월", "start": "10:00", "end": "11:30"}, {"day": "수", "start": "10:00", "end": "11:30"}],
    "room": "",
    "target_year": 2,
    "capacity": 0,
    "notes": "",
    "is_micro": false
  },
  {
    "course_code": "172502",
    "section": "01",
    "course_name": "캡스톤디자인(지역발전)",
    "professor": "홍성우",
    "credits": 3,
    "hours": 4,
    "category": "major",
    "classification": "전선",
    "college": "공공인재대학",
    "department": "행정정보학과",
    "schedule_raw": "금11:30-13:00",
    "times": [{"day": "금", "start": "11:30", "end": "13:00"}],
    "room": "사105 - 세미나/V실",
    "target_year": 3,
    "capacity": 0,
    "notes": "대화형전공",
    "is_micro": false
  },
  {
    "course_code": "175036",
    "section": "01",
    "course_name": "전산회계실무",
    "professor": "고대유",
    "credits": 3,
    "hours": 6,
    "category": "major",
    "classification": "전선",
    "college": "공공인재대학",
    "department": "행정정보학과",
    "schedule_raw": "화13:30-15:00, 목13:30-15:00",
    "times": [{"day": "화", "start": "13:30", "end": "15:00"}, {"day": "목", "start": "13:30", "end": "15:00"}],
    "room": "융복 406 정보실습실H",
    "target_year": 3,
    "capacity": 0,
    "notes": "",
    "is_micro": false
  },
  {
    "course_code": "175037",
    "section": "01",
    "course_name": "행정법개론",
    "professor": "이진규",
    "credits": 3,
    "hours": 6,
    "category": "major",
    "classification": "전선",
    "college": "공공인재대학",
    "department": "행정정보학과",
    "schedule_raw": "화15:00-18:00",
    "times": [{"day": "화", "start": "15:00", "end": "18:00"}],
    "room": "",
    "target_year": 3,
    "capacity": 0,
    "notes": "",
    "is_micro": false
  },
  {
    "course_code": "172054",
    "section": "01",
    "course_name": "공기업론",
    "professor": "김종관",
    "credits": 3,
    "hours": 6,
    "category": "major",
    "classification": "전선",
    "college": "공공인재대학",
    "department": "행정정보학과",
    "schedule_raw": "월07:40-10:30, 수13:30-15:00",
    "times": [{"day": "월", "start": "07:40", "end": "10:30"}, {"day": "수", "start": "13:30", "end": "15:00"}],
    "room": "",
    "target_year": 3,
    "capacity": 0,
    "notes": "",
    "is_micro": false
  },
  {
    "course_code": "172602",
    "section": "01",
    "course_name": "AI행정실무",
    "professor": "윤나나",
    "credits": 3,
    "hours": 6,
    "category": "major",
    "classification": "전선",
    "college": "공공인재대학",
    "department": "행정정보학과",
    "schedule_raw": "",
    "times": [],
    "room": "",
    "target_year": 3,
    "capacity": 0,
    "notes": "",
    "is_micro": false
  },
  {
    "course_code": "175038",
    "section": "01",
    "course_name": "정보공공이론",
    "professor": "홍성우",
    "credits": 3,
    "hours": 6,
    "category": "major",
    "classification": "전선",
    "college": "공공인재대학",
    "department": "행정정보학과",
    "schedule_raw": "목14:30-17:30",
    "times": [{"day": "목", "start": "14:30", "end": "17:30"}],
    "room": "사109 - 고양A/V강의실",
    "target_year": 4,
    "capacity": 0,
    "notes": "",
    "is_micro": false
  },
  {
    "course_code": "175039",
    "section": "01",
    "course_name": "빅데이터시각화",
    "professor": "윤나나",
    "credits": 3,
    "hours": 6,
    "category": "major",
    "classification": "전선",
    "college": "공공인재대학",
    "department": "행정정보학과",
    "schedule_raw": "목15:30-17:00",
    "times": [{"day": "목", "start": "15:30", "end": "17:00"}],
    "room": "사 310 스마트강의실",
    "target_year": 4,
    "capacity": 0,
    "notes": "",
    "is_micro": false
  },
  {
    "course_code": "191001",
    "section": "01",
    "course_name": "***사회복지학개론",
    "professor": "안지연",
    "credits": 3,
    "hours": 6,
    "category": "major",
    "classification": "전선",
    "college": "공공인재대학",
    "department": "사회복지학과",
    "schedule_raw": "화13:30-15:00, 금13:30-15:00",
    "times": [{"day": "화", "start": "13:30", "end": "15:00"}, {"day": "금", "start": "13:30", "end": "15:00"}],
    "room": "사104 - 세미나A/V실",
    "target_year": 1,
    "capacity": 0,
    "notes": "1학년만 수강신청",
    "is_micro": false
  },
  {
    "course_code": "192601",
    "section": "01",
    "course_name": "문화다양성과사회복지",
    "professor": "안지연",
    "credits": 3,
    "hours": 6,
    "category": "major",
    "classification": "전선",
    "college": "공공인재대학",
    "department": "사회복지학과",
    "schedule_raw": "화11:30-13:00, 금11:30-13:00",
    "times": [{"day": "화", "start": "11:30", "end": "13:00"}, {"day": "금", "start": "11:30", "end": "13:00"}],
    "room": "사208 - 강의실",
    "target_year": 1,
    "capacity": 0,
    "notes": "",
    "is_micro": false
  },
  {
    "course_code": "195014",
    "section": "01",
    "course_name": "사회복지현장입문실습",
    "professor": "배종철",
    "credits": 3,
    "hours": 4,
    "category": "major",
    "classification": "전선",
    "college": "공공인재대학",
    "department": "사회복지학과",
    "schedule_raw": "월13:30-17:30",
    "times": [{"day": "월", "start": "13:30", "end": "17:30"}],
    "room": "사208 - 강의실",
    "target_year": 1,
    "capacity": 0,
    "notes": "",
    "is_micro": false
  },
  {
    "course_code": "192007",
    "section": "01",
    "course_name": "가족복지론",
    "professor": "김소희",
    "credits": 3,
    "hours": 6,
    "category": "major",
    "classification": "전선",
    "college": "공공인재대학",
    "department": "사회복지학과",
    "schedule_raw": "화11:30-13:00, 금11:30-13:00",
    "times": [{"day": "화", "start": "11:30", "end": "13:00"}, {"day": "금", "start": "11:30", "end": "13:00"}],
    "room": "사209 - e강의실",
    "target_year": 2,
    "capacity": 0,
    "notes": "정복비사복지플립러닝10시간진행",
    "is_micro": true
  },
  {
    "course_code": "192007",
    "section": "02",
    "course_name": "가족복지론",
    "professor": "김소희",
    "credits": 3,
    "hours": 6,
    "category": "major",
    "classification": "전선",
    "college": "공공인재대학",
    "department": "사회복지학과",
    "schedule_raw": "화14:00-15:30, 금14:00-15:30",
    "times": [{"day": "화", "start": "14:00", "end": "15:30"}, {"day": "금", "start": "14:00", "end": "15:30"}],
    "room": "",
    "target_year": 2,
    "capacity": 0,
    "notes": "",
    "is_micro": true
  },
  {
    "course_code": "192017",
    "section": "01",
    "course_name": "장애인복지론",
    "professor": "배종철",
    "credits": 3,
    "hours": 6,
    "category": "major",
    "classification": "전선",
    "college": "공공인재대학",
    "department": "사회복지학과",
    "schedule_raw": "월10:00-11:30, 수10:30-12:00",
    "times": [{"day": "월", "start": "10:00", "end": "11:30"}, {"day": "수", "start": "10:30", "end": "12:00"}],
    "room": "사1109-2. 사복 e-강의실",
    "target_year": 2,
    "capacity": 0,
    "notes": "정복비사복지플립러닝사회복지학과",
    "is_micro": true
  },
  {
    "course_code": "192027",
    "section": "01",
    "course_name": "사회복지조사론",
    "professor": "이수비",
    "credits": 3,
    "hours": 6,
    "category": "major",
    "classification": "전선",
    "college": "공공인재대학",
    "department": "사회복지학과",
    "schedule_raw": "월14:00-15:30, 수14:00-15:30",
    "times": [{"day": "월", "start": "14:00", "end": "15:30"}, {"day": "수", "start": "14:00", "end": "15:30"}],
    "room": "사 - e강의실",
    "target_year": 2,
    "capacity": 0,
    "notes": "",
    "is_micro": false
  },
  {
    "course_code": "192027",
    "section": "02",
    "course_name": "사회복지조사론",
    "professor": "이수비",
    "credits": 3,
    "hours": 6,
    "category": "major",
    "classification": "전선",
    "college": "공공인재대학",
    "department": "사회복지학과",
    "schedule_raw": "월10:00-11:30, 수11:30-13:00",
    "times": [{"day": "월", "start": "10:00", "end": "11:30"}, {"day": "수", "start": "11:30", "end": "13:00"}],
    "room": "",
    "target_year": 2,
    "capacity": 0,
    "notes": "",
    "is_micro": false
  },
  {
    "course_code": "195008",
    "section": "01",
    "course_name": "사회복지법제와실천",
    "professor": "안지연",
    "credits": 3,
    "hours": 6,
    "category": "major",
    "classification": "전선",
    "college": "공공인재대학",
    "department": "사회복지학과",
    "schedule_raw": "화14:00-15:30, 금14:00-15:30",
    "times": [{"day": "화", "start": "14:00", "end": "15:30"}, {"day": "금", "start": "14:00", "end": "15:30"}],
    "room": "",
    "target_year": 2,
    "capacity": 0,
    "notes": "",
    "is_micro": false
  },
  {
    "course_code": "192031",
    "section": "01",
    "course_name": "사회복지실천기술론",
    "professor": "이수비",
    "credits": 3,
    "hours": 6,
    "category": "major",
    "classification": "전선",
    "college": "공공인재대학",
    "department": "사회복지학과",
    "schedule_raw": "화12:00-13:30, 금12:00-13:30",
    "times": [{"day": "화", "start": "12:00", "end": "13:30"}, {"day": "금", "start": "12:00", "end": "13:30"}],
    "room": "",
    "target_year": 2,
    "capacity": 0,
    "notes": "정복비사학복지사회복지플립러닝10시간진행",
    "is_micro": false
  },
  {
    "course_code": "192036",
    "section": "01",
    "course_name": "사회복지정책론",
    "professor": "김소희",
    "credits": 3,
    "hours": 6,
    "category": "major",
    "classification": "전선",
    "college": "공공인재대학",
    "department": "사회복지학과",
    "schedule_raw": "화15:30-17:00, 금15:30-17:00",
    "times": [{"day": "화", "start": "15:30", "end": "17:00"}, {"day": "금", "start": "15:30", "end": "17:00"}],
    "room": "",
    "target_year": 3,
    "capacity": 0,
    "notes": "정복비사복지(플립러닝사회복지학과비대면수업10시간진행)",
    "is_micro": false
  },
  {
    "course_code": "192043",
    "section": "01",
    "course_name": "프로그램개발과평가",
    "professor": "김소희",
    "credits": 3,
    "hours": 6,
    "category": "major",
    "classification": "전선",
    "college": "공공인재대학",
    "department": "사회복지학과",
    "schedule_raw": "금09:30-12:30",
    "times": [{"day": "금", "start": "09:30", "end": "12:30"}],
    "room": "사205 - 강의실",
    "target_year": 3,
    "capacity": 0,
    "notes": "",
    "is_micro": true
  },
  {
    "course_code": "195011",
    "section": "01",
    "course_name": "학교사회복지론",
    "professor": "정명희",
    "credits": 3,
    "hours": 6,
    "category": "major",
    "classification": "전선",
    "college": "공공인재대학",
    "department": "사회복지학과",
    "schedule_raw": "금10:00-13:30",
    "times": [{"day": "금", "start": "10:00", "end": "13:30"}],
    "room": "사201 - e강의실",
    "target_year": 3,
    "capacity": 0,
    "notes": "정복비사복지사회복지플립러닝10시간진행",
    "is_micro": false
  },
  {
    "course_code": "192015",
    "section": "01",
    "course_name": "사회복지현장실습III",
    "professor": "배종철",
    "credits": 3,
    "hours": 4,
    "category": "major",
    "classification": "전선",
    "college": "공공인재대학",
    "department": "사회복지학과",
    "schedule_raw": "목13:30-17:30",
    "times": [{"day": "목", "start": "13:30", "end": "17:30"}],
    "room": "사104 - 세미나A/V실",
    "target_year": 3,
    "capacity": 0,
    "notes": "",
    "is_micro": false
  },
  {
    "course_code": "192056",
    "section": "01",
    "course_name": "사례관리론",
    "professor": "정명희",
    "credits": 3,
    "hours": 4,
    "category": "major",
    "classification": "전선",
    "college": "공공인재대학",
    "department": "사회복지학과",
    "schedule_raw": "목13:30-17:30",
    "times": [{"day": "목", "start": "13:30", "end": "17:30"}],
    "room": "사201 - e-강의실",
    "target_year": 3,
    "capacity": 0,
    "notes": "",
    "is_micro": false
  },
  {
    "course_code": "192602",
    "section": "01",
    "course_name": "AI기반사회문제해결과복지실무",
    "professor": "이수비",
    "credits": 3,
    "hours": 4,
    "category": "major",
    "classification": "전선",
    "college": "공공인재대학",
    "department": "사회복지학과",
    "schedule_raw": "수11:30-15:30",
    "times": [{"day": "수", "start": "11:30", "end": "15:30"}],
    "room": "정복 403 정보실습실I, 정복 404 정보실습실J",
    "target_year": 4,
    "capacity": 0,
    "notes": "사회복지학과(비대면수업없음)",
    "is_micro": false
  },
  {
    "course_code": "195009",
    "section": "01",
    "course_name": "정신건강사회복지론",
    "professor": "이수비",
    "credits": 3,
    "hours": 6,
    "category": "major",
    "classification": "전선",
    "college": "공공인재대학",
    "department": "사회복지학과",
    "schedule_raw": "화10:30-13:30",
    "times": [{"day": "화", "start": "10:30", "end": "13:30"}],
    "room": "사201 - e-강의실",
    "target_year": 4,
    "capacity": 0,
    "notes": "사회복지학과(비대면수업10시간진행)",
    "is_micro": false
  },
  {
    "course_code": "191004",
    "section": "01",
    "course_name": "보육학개론",
    "professor": "김영아",
    "credits": 3,
    "hours": 6,
    "category": "major",
    "classification": "전선",
    "college": "공공인재대학",
    "department": "아동학과",
    "schedule_raw": "화13:30-15:00, 목13:30-15:00",
    "times": [{"day": "화", "start": "13:30", "end": "15:00"}, {"day": "목", "start": "13:30", "end": "15:00"}],
    "room": "e-A/V강의실",
    "target_year": 1,
    "capacity": 0,
    "notes": "융합인이티(플립러닝비대면수업10시간진행)",
    "is_micro": false
  },
  {
    "course_code": "191005",
    "section": "01",
    "course_name": "***영유아발달",
    "professor": "김영아",
    "credits": 3,
    "hours": 6,
    "category": "major",
    "classification": "전선",
    "college": "공공인재대학",
    "department": "아동학과",
    "schedule_raw": "화12:00-13:30, 목11:30-13:00",
    "times": [{"day": "화", "start": "12:00", "end": "13:30"}, {"day": "목", "start": "11:30", "end": "13:00"}],
    "room": "",
    "target_year": 1,
    "capacity": 0,
    "notes": "전공입문 교과목임",
    "is_micro": false
  },
  {
    "course_code": "191005",
    "section": "02",
    "course_name": "***영유아발달",
    "professor": "손지향",
    "credits": 3,
    "hours": 6,
    "category": "major",
    "classification": "전선",
    "college": "공공인재대학",
    "department": "아동학과",
    "schedule_raw": "목10:00-13:00",
    "times": [{"day": "목", "start": "10:00", "end": "13:00"}],
    "room": "사110 - 일반강의실",
    "target_year": 1,
    "capacity": 0,
    "notes": "",
    "is_micro": false
  },
  {
    "course_code": "234026",
    "section": "01",
    "course_name": "건강가정론",
    "professor": "최경",
    "credits": 3,
    "hours": 6,
    "category": "major",
    "classification": "전선",
    "college": "공공인재대학",
    "department": "아동학과",
    "schedule_raw": "월10:00-11:30",
    "times": [{"day": "월", "start": "10:00", "end": "11:30"}],
    "room": "e-A/V강의실",
    "target_year": 1,
    "capacity": 0,
    "notes": "융합인이티(플립러닝비대면수업10시간진행)",
    "is_micro": true
  },
  {
    "course_code": "234026",
    "section": "02",
    "course_name": "건강가정론",
    "professor": "김영아",
    "credits": 3,
    "hours": 6,
    "category": "major",
    "classification": "전선",
    "college": "공공인재대학",
    "department": "아동학과",
    "schedule_raw": "금12:30-13:00",
    "times": [{"day": "금", "start": "12:30", "end": "13:00"}],
    "room": "사110 - 일반강의실",
    "target_year": 1,
    "capacity": 0,
    "notes": "",
    "is_micro": true
  },
  {
    "course_code": "232045",
    "section": "01",
    "course_name": "아동미술",
    "professor": "김형모",
    "credits": 3,
    "hours": 6,
    "category": "major",
    "classification": "전선",
    "college": "공공인재대학",
    "department": "아동학과",
    "schedule_raw": "",
    "times": [],
    "room": "",
    "target_year": 2,
    "capacity": 0,
    "notes": "융합인이티(플립러닝비대면수업10시간진행)",
    "is_micro": false
  },
  {
    "course_code": "234011",
    "section": "01",
    "course_name": "보육과정",
    "professor": "최경",
    "credits": 3,
    "hours": 6,
    "category": "major",
    "classification": "전선",
    "college": "공공인재대학",
    "department": "아동학과",
    "schedule_raw": "화10:00-11:30, 화11:30-13:00",
    "times": [{"day": "화", "start": "10:00", "end": "11:30"}, {"day": "화", "start": "11:30", "end": "13:00"}],
    "room": "e-A/V강의실",
    "target_year": 2,
    "capacity": 0,
    "notes": "융합인이티(플립러닝비대면수업10시간진행)",
    "is_micro": false
  },
  {
    "course_code": "234011",
    "section": "02",
    "course_name": "보육과정",
    "professor": "이혜정",
    "credits": 3,
    "hours": 6,
    "category": "major",
    "classification": "전선",
    "college": "공공인재대학",
    "department": "아동학과",
    "schedule_raw": "화11:30-13:00",
    "times": [{"day": "화", "start": "11:30", "end": "13:00"}],
    "room": "",
    "target_year": 2,
    "capacity": 0,
    "notes": "",
    "is_micro": false
  },
  {
    "course_code": "234012",
    "section": "01",
    "course_name": "아동관찰및행동연구",
    "professor": "손지향",
    "credits": 3,
    "hours": 6,
    "category": "major",
    "classification": "전선",
    "college": "공공인재대학",
    "department": "아동학과",
    "schedule_raw": "월13:30-16:30",
    "times": [{"day": "월", "start": "13:30", "end": "16:30"}],
    "room": "",
    "target_year": 2,
    "capacity": 0,
    "notes": "",
    "is_micro": false
  },
  {
    "course_code": "234014",
    "section": "01",
    "course_name": "놀이지도",
    "professor": "김형희",
    "credits": 3,
    "hours": 6,
    "category": "major",
    "classification": "전선",
    "college": "공공인재대학",
    "department": "아동학과",
    "schedule_raw": "화13:30-15:00, 목13:30-15:00",
    "times": [{"day": "화", "start": "13:30", "end": "15:00"}, {"day": "목", "start": "13:30", "end": "15:00"}],
    "room": "e-A/V강의실",
    "target_year": 2,
    "capacity": 0,
    "notes": "융합인이티(플립러닝비대면수업10시간진행)",
    "is_micro": false
  },
  {
    "course_code": "234022",
    "section": "01",
    "course_name": "아동동작",
    "professor": "최경",
    "credits": 3,
    "hours": 6,
    "category": "major",
    "classification": "전선",
    "college": "공공인재대학",
    "department": "아동학과",
    "schedule_raw": "목09:30-12:30",
    "times": [{"day": "목", "start": "09:30", "end": "12:30"}],
    "room": "사110 - 일반강의실",
    "target_year": 2,
    "capacity": 0,
    "notes": "",
    "is_micro": false
  },
  {
    "course_code": "234023",
    "section": "01",
    "course_name": "아동수학지도",
    "professor": "김형연",
    "credits": 3,
    "hours": 6,
    "category": "major",
    "classification": "전선",
    "college": "공공인재대학",
    "department": "아동학과",
    "schedule_raw": "목13:30-15:00",
    "times": [{"day": "목", "start": "13:30", "end": "15:00"}],
    "room": "e-A/V강의실",
    "target_year": 2,
    "capacity": 0,
    "notes": "융합인이티(플립러닝비대면수업10시간진행)",
    "is_micro": false
  },
  {
    "course_code": "235006",
    "section": "01",
    "course_name": "영유아교수방법론",
    "professor": "신지현",
    "credits": 3,
    "hours": 6,
    "category": "major",
    "classification": "전선",
    "college": "공공인재대학",
    "department": "아동학과",
    "schedule_raw": "목14:30-17:30",
    "times": [{"day": "목", "start": "14:30", "end": "17:30"}],
    "room": "",
    "target_year": 3,
    "capacity": 0,
    "notes": "",
    "is_micro": false
  },
  {
    "course_code": "235017",
    "section": "01",
    "course_name": "부모교육론",
    "professor": "김영아",
    "credits": 3,
    "hours": 6,
    "category": "major",
    "classification": "전선",
    "college": "공공인재대학",
    "department": "아동학과",
    "schedule_raw": "화11:30-13:00",
    "times": [{"day": "화", "start": "11:30", "end": "13:00"}],
    "room": "",
    "target_year": 3,
    "capacity": 0,
    "notes": "",
    "is_micro": false
  },
  {
    "course_code": "232023",
    "section": "01",
    "course_name": "보육실습",
    "professor": "이혜정",
    "credits": 3,
    "hours": 6,
    "category": "major",
    "classification": "전선",
    "college": "공공인재대학",
    "department": "아동학과",
    "schedule_raw": "",
    "times": [],
    "room": "",
    "target_year": 4,
    "capacity": 0,
    "notes": "",
    "is_micro": false
  },
  {
    "course_code": "211159",
    "section": "01",
    "course_name": "휴먼커뮤니케이션",
    "professor": "조수산",
    "credits": 3,
    "hours": 6,
    "category": "major",
    "classification": "전선",
    "college": "공공인재대학",
    "department": "미디어커뮤니케이션학과",
    "schedule_raw": "월11:30-15:00, 목13:30-15:00",
    "times": [{"day": "월", "start": "11:30", "end": "15:00"}, {"day": "목", "start": "13:30", "end": "15:00"}],
    "room": "사509 - A/V강의실",
    "target_year": 1,
    "capacity": 0,
    "notes": "융합,인이티10시간추가진행",
    "is_micro": false
  },
  {
    "course_code": "215003",
    "section": "01",
    "course_name": "미디어와의이해",
    "professor": "조수산",
    "credits": 3,
    "hours": 6,
    "category": "major",
    "classification": "전필",
    "college": "공공인재대학",
    "department": "미디어커뮤니케이션학과",
    "schedule_raw": "월13:30-15:00, 수13:30-15:00",
    "times": [{"day": "월", "start": "13:30", "end": "15:00"}, {"day": "수", "start": "13:30", "end": "15:00"}],
    "room": "사 408",
    "target_year": 1,
    "capacity": 0,
    "notes": "융합,인이티10시간추가진행",
    "is_micro": true
  },
  {
    "course_code": "232500",
    "section": "01",
    "course_name": "***미디어커뮤니케이션입문",
    "professor": "황지현",
    "credits": 3,
    "hours": 6,
    "category": "major",
    "classification": "전필",
    "college": "공공인재대학",
    "department": "미디어커뮤니케이션학과",
    "schedule_raw": "화11:30-13:00, 목11:30-13:00",
    "times": [{"day": "화", "start": "11:30", "end": "13:00"}, {"day": "목", "start": "11:30", "end": "13:00"}],
    "room": "사509 - A/V강의실",
    "target_year": 1,
    "capacity": 0,
    "notes": "전공입문 교과목임",
    "is_micro": false
  },
  {
    "course_code": "214011",
    "section": "01",
    "course_name": "홍보과전자적",
    "professor": "이용훈",
    "credits": 3,
    "hours": 6,
    "category": "major",
    "classification": "전선",
    "college": "공공인재대학",
    "department": "미디어커뮤니케이션학과",
    "schedule_raw": "월11:30-13:00, 목11:30-13:00",
    "times": [{"day": "월", "start": "11:30", "end": "13:00"}, {"day": "목", "start": "11:30", "end": "13:00"}],
    "room": "사 313 - e-스마트강의실(사)",
    "target_year": 2,
    "capacity": 0,
    "notes": "2018학번 이상은 타 학과의 입문 교과목 이수 시, 최대 6학점까지 일선이 아닌 전선으로 인정",
    "is_micro": false
  },
  {
    "course_code": "215004",
    "section": "01",
    "course_name": "비주얼커뮤니케이션제작",
    "professor": "이여람",
    "credits": 3,
    "hours": 4,
    "category": "major",
    "classification": "전선",
    "college": "공공인재대학",
    "department": "미디어커뮤니케이션학과",
    "schedule_raw": "수13:30-16:30",
    "times": [{"day": "수", "start": "13:30", "end": "16:30"}],
    "room": "",
    "target_year": 2,
    "capacity": 0,
    "notes": "",
    "is_micro": false
  },
  {
    "course_code": "215008",
    "section": "01",
    "course_name": "PR론",
    "professor": "황지현",
    "credits": 3,
    "hours": 6,
    "category": "major",
    "classification": "전선",
    "college": "공공인재대학",
    "department": "미디어커뮤니케이션학과",
    "schedule_raw": "월15:30-17:00, 수15:30-17:00",
    "times": [{"day": "월", "start": "15:30", "end": "17:00"}, {"day": "수", "start": "15:30", "end": "17:00"}],
    "room": "",
    "target_year": 2,
    "capacity": 0,
    "notes": "",
    "is_micro": true
  },
  {
    "course_code": "215008",
    "section": "02",
    "course_name": "PR론",
    "professor": "김태영",
    "credits": 3,
    "hours": 6,
    "category": "major",
    "classification": "전선",
    "college": "공공인재대학",
    "department": "미디어커뮤니케이션학과",
    "schedule_raw": "목20:30-21:20",
    "times": [{"day": "목", "start": "20:30", "end": "21:20"}],
    "room": "e-learning(온라인2",
    "target_year": 2,
    "capacity": 0,
    "notes": "",
    "is_micro": true
  },
  {
    "course_code": "215018",
    "section": "01",
    "course_name": "스포츠와미디어저널리즘이미해",
    "professor": "이장훈",
    "credits": 3,
    "hours": 6,
    "category": "major",
    "classification": "전선",
    "college": "공공인재대학",
    "department": "미디어커뮤니케이션학과",
    "schedule_raw": "수13:30-15:00, 금10:00-11:30",
    "times": [{"day": "수", "start": "13:30", "end": "15:00"}, {"day": "금", "start": "10:00", "end": "11:30"}],
    "room": "사201 - 으A/V강의실",
    "target_year": 2,
    "capacity": 0,
    "notes": "",
    "is_micro": false
  },
  {
    "course_code": "215030",
    "section": "01",
    "course_name": "영상제작프로젝트",
    "professor": "김연성",
    "credits": 3,
    "hours": 4,
    "category": "major",
    "classification": "전선",
    "college": "공공인재대학",
    "department": "미디어커뮤니케이션학과",
    "schedule_raw": "월11:30-13:00, 목11:30-13:00",
    "times": [{"day": "월", "start": "11:30", "end": "13:00"}, {"day": "목", "start": "11:30", "end": "13:00"}],
    "room": "",
    "target_year": 2,
    "capacity": 0,
    "notes": "",
    "is_micro": false
  },
  {
    "course_code": "214017",
    "section": "01",
    "course_name": "미디어조사방법론",
    "professor": "이장호",
    "credits": 3,
    "hours": 6,
    "category": "major",
    "classification": "전필",
    "college": "공공인재대학",
    "department": "미디어커뮤니케이션학과",
    "schedule_raw": "화14:00-15:30, 목14:00-15:30",
    "times": [{"day": "화", "start": "14:00", "end": "15:30"}, {"day": "목", "start": "14:00", "end": "15:30"}],
    "room": "사209 - 여/사서313...",
    "target_year": 3,
    "capacity": 0,
    "notes": "정독물사용(플립러닝비대면수업10시간진행)",
    "is_micro": false
  },
  {
    "course_code": "215010",
    "section": "01",
    "course_name": "광고전략기획",
    "professor": "조제현",
    "credits": 3,
    "hours": 6,
    "category": "major",
    "classification": "전선",
    "college": "공공인재대학",
    "department": "미디어커뮤니케이션학과",
    "schedule_raw": "",
    "times": [],
    "room": "",
    "target_year": 3,
    "capacity": 0,
    "notes": "",
    "is_micro": false
  },
  {
    "course_code": "215012",
    "section": "01",
    "course_name": "모바일콘텐츠제작",
    "professor": "예지",
    "credits": 3,
    "hours": 4,
    "category": "major",
    "classification": "전선",
    "college": "공공인재대학",
    "department": "미디어커뮤니케이션학과",
    "schedule_raw": "수13:30-17:30",
    "times": [{"day": "수", "start": "13:30", "end": "17:30"}],
    "room": "사208 - e강의실",
    "target_year": 3,
    "capacity": 0,
    "notes": "",
    "is_micro": false
  },
  {
    "course_code": "215022",
    "section": "01",
    "course_name": "문화콘텐츠",
    "professor": "조수산",
    "credits": 3,
    "hours": 6,
    "category": "major",
    "classification": "전선",
    "college": "공공인재대학",
    "department": "미디어커뮤니케이션학과",
    "schedule_raw": "화11:30-13:00",
    "times": [{"day": "화", "start": "11:30", "end": "13:00"}],
    "room": "",
    "target_year": 3,
    "capacity": 0,
    "notes": "",
    "is_micro": true
  },
  {
    "course_code": "215028",
    "section": "01",
    "course_name": "광고와사회",
    "professor": "조재현",
    "credits": 3,
    "hours": 6,
    "category": "major",
    "classification": "전선",
    "college": "공공인재대학",
    "department": "미디어커뮤니케이션학과",
    "schedule_raw": "화10:00-11:30",
    "times": [{"day": "화", "start": "10:00", "end": "11:30"}],
    "room": "사 - e-강의실",
    "target_year": 3,
    "capacity": 0,
    "notes": "",
    "is_micro": false
  },
  {
    "course_code": "214019",
    "section": "01",
    "course_name": "광고홍보실습",
    "professor": "조재현",
    "credits": 3,
    "hours": 4,
    "category": "major",
    "classification": "전선",
    "college": "공공인재대학",
    "department": "미디어커뮤니케이션학과",
    "schedule_raw": "",
    "times": [],
    "room": "",
    "target_year": 4,
    "capacity": 0,
    "notes": "",
    "is_micro": false
  },
  {
    "course_code": "232501",
    "section": "01",
    "course_name": "창작형세미나(미디어커뮤니케이션)",
    "professor": "황지현",
    "credits": 3,
    "hours": 4,
    "category": "major",
    "classification": "전선",
    "college": "공공인재대학",
    "department": "미디어커뮤니케이션학과",
    "schedule_raw": "",
    "times": [],
    "room": "",
    "target_year": 4,
    "capacity": 0,
    "notes": "",
    "is_micro": false
  },
  {
    "course_code": "221004",
    "section": "01",
    "course_name": "***문헌정보학개론",
    "professor": "김순",
    "credits": 3,
    "hours": 6,
    "category": "major",
    "classification": "전필",
    "college": "공공인재대학",
    "department": "문헌정보학과",
    "schedule_raw": "화13:30-16:30",
    "times": [{"day": "화", "start": "13:30", "end": "16:30"}],
    "room": "",
    "target_year": 1,
    "capacity": 0,
    "notes": "전공입문 교과목임",
    "is_micro": false
  },
  {
    "course_code": "222001",
    "section": "01",
    "course_name": "고전자료의이해",
    "professor": "유부현",
    "credits": 3,
    "hours": 6,
    "category": "major",
    "classification": "전선",
    "college": "공공인재대학",
    "department": "문헌정보학과",
    "schedule_raw": "목12:00-13:30",
    "times": [{"day": "목", "start": "12:00", "end": "13:30"}],
    "room": "사208 - 으-A/V강의실",
    "target_year": 1,
    "capacity": 0,
    "notes": "2018학번 이상은 타 학과의 입문 교과목 이수 시, 최대 6학점까지 일선이 아닌 전선으로 인정",
    "is_micro": false
  },
  {
    "course_code": "225007",
    "section": "01",
    "course_name": "지식정보사회론",
    "professor": "송민선",
    "credits": 3,
    "hours": 6,
    "category": "major",
    "classification": "전선",
    "college": "공공인재대학",
    "department": "문헌정보학과",
    "schedule_raw": "월14:30-17:30",
    "times": [{"day": "월", "start": "14:30", "end": "17:30"}],
    "room": "사208 - 으-A/V강의실",
    "target_year": 1,
    "capacity": 0,
    "notes": "",
    "is_micro": false
  },
  {
    "course_code": "225024",
    "section": "01",
    "course_name": "학교도서관경영의이해",
    "professor": "심효정",
    "credits": 3,
    "hours": 6,
    "category": "major",
    "classification": "전선",
    "college": "공공인재대학",
    "department": "문헌정보학과",
    "schedule_raw": "화11:30-13:00, 목13:30-15:00",
    "times": [{"day": "화", "start": "11:30", "end": "13:00"}, {"day": "목", "start": "13:30", "end": "15:00"}],
    "room": "",
    "target_year": 1,
    "capacity": 0,
    "notes": "",
    "is_micro": false
  },
  {
    "course_code": "221005",
    "section": "01",
    "course_name": "문헌분류론",
    "professor": "윤현수",
    "credits": 3,
    "hours": 6,
    "category": "major",
    "classification": "전필",
    "college": "공공인재대학",
    "department": "문헌정보학과",
    "schedule_raw": "월14:00-15:30, 수15:30-17:00",
    "times": [{"day": "월", "start": "14:00", "end": "15:30"}, {"day": "수", "start": "15:30", "end": "17:00"}],
    "room": "사208 - 으-A/V강의실",
    "target_year": 2,
    "capacity": 0,
    "notes": "",
    "is_micro": false
  },
  {
    "course_code": "222005",
    "section": "01",
    "course_name": "서지학(문헌학)개론",
    "professor": "유부현",
    "credits": 3,
    "hours": 6,
    "category": "major",
    "classification": "전선",
    "college": "공공인재대학",
    "department": "문헌정보학과",
    "schedule_raw": "화12:30-15:30, 목10:00-11:30",
    "times": [{"day": "화", "start": "12:30", "end": "15:30"}, {"day": "목", "start": "10:00", "end": "11:30"}],
    "room": "",
    "target_year": 2,
    "capacity": 0,
    "notes": "문헌정보학과마이크로실습실",
    "is_micro": false
  },
  {
    "course_code": "222501",
    "section": "01",
    "course_name": "데이터사이언스의이해",
    "professor": "송민선",
    "credits": 3,
    "hours": 6,
    "category": "major",
    "classification": "전선",
    "college": "공공인재대학",
    "department": "문헌정보학과",
    "schedule_raw": "월10:00-11:30, 수10:00-11:30",
    "times": [{"day": "월", "start": "10:00", "end": "11:30"}, {"day": "수", "start": "10:00", "end": "11:30"}],
    "room": "사208 - 으자A/V강의실",
    "target_year": 2,
    "capacity": 0,
    "notes": "",
    "is_micro": true
  },
  {
    "course_code": "225010",
    "section": "01",
    "course_name": "도서관정보센터경영이론",
    "professor": "최지영",
    "credits": 3,
    "hours": 6,
    "category": "major",
    "classification": "전선",
    "college": "공공인재대학",
    "department": "문헌정보학과",
    "schedule_raw": "수09:30-12:30",
    "times": [{"day": "수", "start": "09:30", "end": "12:30"}],
    "room": "사208 - 으자A/V강의실",
    "target_year": 2,
    "capacity": 0,
    "notes": "",
    "is_micro": false
  },
  {
    "course_code": "222026",
    "section": "01",
    "course_name": "고서감정법",
    "professor": "유부현",
    "credits": 3,
    "hours": 6,
    "category": "major",
    "classification": "전선",
    "college": "공공인재대학",
    "department": "문헌정보학과",
    "schedule_raw": "월09:30-12:30, 수09:30-12:30",
    "times": [{"day": "월", "start": "09:30", "end": "12:30"}, {"day": "수", "start": "09:30", "end": "12:30"}],
    "room": "",
    "target_year": 2,
    "capacity": 0,
    "notes": "",
    "is_micro": false
  },
  {
    "course_code": "222044",
    "section": "01",
    "course_name": "자료조직연습",
    "professor": "최지영",
    "credits": 3,
    "hours": 6,
    "category": "major",
    "classification": "전선",
    "college": "공공인재대학",
    "department": "문헌정보학과",
    "schedule_raw": "수13:30-15:00, 금13:30-15:00",
    "times": [{"day": "수", "start": "13:30", "end": "15:00"}, {"day": "금", "start": "13:30", "end": "15:00"}],
    "room": "",
    "target_year": 3,
    "capacity": 0,
    "notes": "정보복원복지학과불가",
    "is_micro": false
  },
  {
    "course_code": "225013",
    "section": "01",
    "course_name": "데이터큐레이션",
    "professor": "송민선",
    "credits": 3,
    "hours": 6,
    "category": "major",
    "classification": "전선",
    "college": "공공인재대학",
    "department": "문헌정보학과",
    "schedule_raw": "화11:30-13:00, 목11:30-13:00",
    "times": [{"day": "화", "start": "11:30", "end": "13:00"}, {"day": "목", "start": "11:30", "end": "13:00"}],
    "room": "",
    "target_year": 3,
    "capacity": 0,
    "notes": "",
    "is_micro": true
  },
  {
    "course_code": "225014",
    "section": "01",
    "course_name": "도서관정보센터경영실습",
    "professor": "이훈",
    "credits": 3,
    "hours": 4,
    "category": "major",
    "classification": "전선",
    "college": "공공인재대학",
    "department": "문헌정보학과",
    "schedule_raw": "화13:00-15:00, 목14:00-15:30",
    "times": [{"day": "화", "start": "13:00", "end": "15:00"}, {"day": "목", "start": "14:00", "end": "15:30"}],
    "room": "",
    "target_year": 3,
    "capacity": 0,
    "notes": "",
    "is_micro": false
  },
  {
    "course_code": "222087",
    "section": "01",
    "course_name": "도서관실습",
    "professor": "심효정",
    "credits": 3,
    "hours": 4,
    "category": "major",
    "classification": "전선",
    "college": "공공인재대학",
    "department": "문헌정보학과",
    "schedule_raw": "수15:30-17:00, 금15:30-17:00",
    "times": [{"day": "수", "start": "15:30", "end": "17:00"}, {"day": "금", "start": "15:30", "end": "17:00"}],
    "room": "",
    "target_year": 3,
    "capacity": 0,
    "notes": "",
    "is_micro": false
  },
  {
    "course_code": "222503",
    "section": "01",
    "course_name": "데이터베이스운영론",
    "professor": "송민선",
    "credits": 3,
    "hours": 6,
    "category": "major",
    "classification": "전선",
    "college": "공공인재대학",
    "department": "문헌정보학과",
    "schedule_raw": "화11:30-13:00, 목11:30-13:00",
    "times": [{"day": "화", "start": "11:30", "end": "13:00"}, {"day": "목", "start": "11:30", "end": "13:00"}],
    "room": "",
    "target_year": 3,
    "capacity": 0,
    "notes": "",
    "is_micro": true
  },
  {
    "course_code": "222504",
    "section": "01",
    "course_name": "취창업세미나(문헌정보)",
    "professor": "심효정",
    "credits": 3,
    "hours": 6,
    "category": "major",
    "classification": "전선",
    "college": "공공인재대학",
    "department": "문헌정보학과",
    "schedule_raw": "금14:30-17:30",
    "times": [{"day": "금", "start": "14:30", "end": "17:30"}],
    "room": "사208 - 으A/V강의실",
    "target_year": 4,
    "capacity": 0,
    "notes": "",
    "is_micro": false
  },
  {
    "course_code": "225017",
    "section": "01",
    "course_name": "도서관정책론",
    "professor": "이장호",
    "credits": 3,
    "hours": 4,
    "category": "major",
    "classification": "전선",
    "college": "공공인재대학",
    "department": "문헌정보학과",
    "schedule_raw": "금14:30-17:30",
    "times": [{"day": "금", "start": "14:30", "end": "17:30"}],
    "room": "사208 - 으A/V강의실",
    "target_year": 4,
    "capacity": 0,
    "notes": "",
    "is_micro": false
  },
  {
    "course_code": "225026",
    "section": "01",
    "course_name": "공공도서관(지역사회와)",
    "professor": "심효정",
    "credits": 3,
    "hours": 4,
    "category": "major",
    "classification": "전선",
    "college": "공공인재대학",
    "department": "문헌정보학과",
    "schedule_raw": "",
    "times": [],
    "room": "",
    "target_year": 4,
    "capacity": 0,
    "notes": "",
    "is_micro": false
  }
]
